rin_string_manip/__init__.py
rin_string_manip/config.yaml
rin_string_manip/log_error.py
rin_string_manip/logging.yaml
rin_string_manip/main.py
rin_string_manip/stopwords.yaml
rin_string_manip/string_funcs.py
rin_string_manip-0.1.2.dist-info/METADATA
rin_string_manip-0.1.2.dist-info/WHEEL
rin_string_manip-0.1.2.dist-info/entry_points.txt
rin_string_manip-0.1.2.dist-info/RECORD
